__init__.py
cli.py
to_yolov8/__init__.py
to_yolov8/converter.py
to_yolov8/yolo_to_yolov8_converter.py
to_yolov8-0.0.1.dist-info/LICENSE.txt
to_yolov8-0.0.1.dist-info/METADATA
to_yolov8-0.0.1.dist-info/WHEEL
to_yolov8-0.0.1.dist-info/entry_points.txt
to_yolov8-0.0.1.dist-info/top_level.txt
to_yolov8-0.0.1.dist-info/RECORD
