Metadata-Version: 2.1
Name: to_yolov8
Version: 0.0.1
Summary: The to_yolov8 package facilitates the conversion of datasets from the YOLO format (Label Studio) to the YOLOv8 format, which is compatible with Ultralytics models. 
Author-email: Dragos Josan <dragosjosan@gmail.com>
License: MIT License
Classifier: Programming Language :: Python :: 3
Classifier: License :: OSI Approved :: MIT License
Classifier: Operating System :: OS Independent
Requires-Python: >=3.7
License-File: LICENSE.txt
Requires-Dist: pytest
Requires-Dist: PyYAML
